[
  {
    "user": "NAHAR",
    "text": "test",
    "date": "2025-04-18T16:21:32.241Z"
  },
  {
    "user": "NAHARASHU",
    "text": "TEST",
    "date": "2025-04-18T16:23:24.559Z"
  },
  {
    "user": "FAKE GUEST",
    "text": "test",
    "date": "2025-04-18T17:07:40.402Z"
  },
  {
    "user": "NAHARASHU",
    "text": "чому ти теж НА",
    "date": "2025-04-18T17:09:35.119Z"
  },
  {
    "user": "NAHARASHU",
    "text": "це важко",
    "date": "2025-04-18T17:09:40.094Z"
  },
  {
    "user": "NAHARASHU",
    "text": "треба інше апі",
    "date": "2025-04-18T17:09:58.979Z"
  },
  {
    "user": "NAHARASHU",
    "text": "ну хай так",
    "date": "2025-04-18T17:25:54.499Z"
  },
  {
    "user": "NAHARASHU",
    "text": "😊😂😢",
    "date": "2025-04-18T17:43:10.455Z"
  },
  {
    "user": "NAHARASHU",
    "text": "😡😊",
    "date": "2025-04-18T17:57:51.166Z"
  },
  {
    "user": "abcd",
    "text": "😎",
    "date": "2025-04-18T19:32:50.669Z"
  },
  {
    "user": "iza.choc",
    "text": "Хм... 🤔",
    "date": "2025-04-18T19:40:15.089Z"
  },
  {
    "user": "abcd",
    "text": "😱",
    "date": "2025-04-21T10:03:11.794Z"
  },
  {
    "user": "NAHARASHU",
    "text": "😱",
    "date": "2025-06-03T13:37:59.119Z"
  },
  {
    "user": "NAHARASHU",
    "text": "😂",
    "date": "2025-06-03T13:38:21.631Z"
  },
  {
    "user": "NAHARASHU",
    "text": "aaa",
    "date": "2025-06-03T13:47:13.285Z"
  },
  {
    "user": "NAHARASHU",
    "text": "idk",
    "date": "2025-06-03T13:47:18.590Z"
  },
  {
    "user": "NAHARASHU",
    "text": "idk \\n idk",
    "date": "2025-06-03T13:47:26.935Z"
  },
  {
    "user": "NAHARASHU",
    "text": "ok",
    "date": "2025-06-03T13:47:31.070Z"
  },
  {
    "user": "testuser",
    "text": "aaaa",
    "date": "2025-06-03T13:47:49.023Z"
  },
  {
    "user": "testuser1212321",
    "text": "😊",
    "date": "2025-06-03T13:48:08.865Z"
  },
  {
    "user": "testuser1212321",
    "text": "tets",
    "date": "2025-06-03T14:25:18.368Z"
  },
  {
    "user": "testuser1212321",
    "text": "test anim",
    "date": "2025-06-03T14:33:58.343Z"
  },
  {
    "user": "testuser1212321",
    "text": "test anim2",
    "date": "2025-06-03T14:38:34.146Z"
  },
  {
    "user": "testuser1212321",
    "text": "😡",
    "date": "2025-06-03T14:38:54.835Z"
  },
  {
    "user": "testuser1212321",
    "text": "aaa",
    "date": "2025-06-03T14:40:50.948Z"
  },
  {
    "user": "testuser1212321",
    "text": "send",
    "date": "2025-06-03T15:10:01.518Z"
  },
  {
    "user": "testuser1212321",
    "text": "```",
    "date": "2025-06-03T15:10:08.903Z"
  },
  {
    "user": "testuser1212321",
    "text": "```js test```",
    "date": "2025-06-03T15:10:29.145Z"
  },
  {
    "user": "testuser1212321",
    "text": "**test**",
    "date": "2025-06-03T15:10:39.690Z"
  },
  {
    "user": "testuser1212321",
    "text": "***test***",
    "date": "2025-06-03T15:10:48.463Z"
  },
  {
    "user": "testuser1212321",
    "text": "# test",
    "date": "2025-06-03T15:10:54.212Z"
  },
  {
    "user": "testuser1212321",
    "text": "<h1>test</h1>",
    "date": "2025-06-03T15:11:27.566Z"
  },
  {
    "user": "testuser1212321",
    "text": "https://example.com",
    "date": "2025-06-03T15:14:33.194Z"
  },
  {
    "user": "testuser1212321",
    "text": "фффф",
    "date": "2025-06-03T17:16:40.902Z",
    "idMsg": "58c02ca1-149e-4c63-89a3-b885ac082055"
  },
  {
    "user": "testuser1212321",
    "text": ">  testuser1212321: фффф (20:16)\nхахахаха",
    "date": "2025-06-03T17:35:48.647Z",
    "idMsg": "45f352c6-d395-4f0c-a3f3-93581d5cf881"
  },
  {
    "user": "testuser1212321",
    "text": ">  testuser1212321: >  testuser1212321: фффф (20:16)хахахаха (20:35)",
    "date": "2025-06-03T17:43:08.125Z",
    "idMsg": "3bef17e4-c984-4493-8359-ae8585b0538f"
  },
  {
    "user": "testuser1212321",
    "text": "ф",
    "date": "2025-06-03T17:50:59.386Z",
    "idMsg": "765351ec-ff3a-4e3b-9d97-2cc5c3d2b7ac"
  },
  {
    "user": "testuser1212321",
    "text": "s",
    "date": "2025-06-03T17:56:29.649Z",
    "idMsg": "24400c26-1cf6-40af-975d-eac00291c92e"
  },
  {
    "user": "testuser1212321",
    "text": "d",
    "date": "2025-06-03T17:56:33.399Z",
    "idMsg": "ec0b1493-73f8-487c-9694-ab8cb1cebadc"
  },
  {
    "user": "testuser1212321",
    "text": "a",
    "date": "2025-06-03T17:56:43.224Z",
    "idMsg": "35f5aea6-3089-427f-b491-91c1a4e4f069"
  },
  {
    "user": "testuser1212321",
    "text": "??",
    "date": "2025-06-03T17:56:47.772Z",
    "idMsg": "d27ff460-9c00-4114-a2b3-7678b3dd2f64"
  },
  {
    "user": "testuser1212321",
    "text": "ф",
    "date": "2025-06-03T17:59:11.797Z",
    "idMsg": "c3592ff7-acb0-4103-9c75-b3b4ccb8ec7a"
  },
  {
    "user": "testuser1212321",
    "text": "ф",
    "date": "2025-06-03T17:59:15.534Z",
    "idMsg": "49359d2f-5c01-469c-a154-b2b915d45a0d"
  },
  {
    "user": "testuser1212321",
    "text": "....",
    "date": "2025-06-03T17:59:19.346Z",
    "idMsg": "95ef046a-f8c0-429d-879b-d3a2c9a0f872"
  },
  {
    "user": "abcd",
    "text": "async function generateCustomUUID() {\n  // 1. Timestamp (в мілісекундах від 1970) у hex\n  const timestamp = Date.now().toString(16);\n\n  // 2. Випадковий рядок (можна будь-який алфавіт)\n  const randomStr = crypto.getRandomValues(new Uint8Array(16))\n    .map(b => b.toString(36)).join('');\n\n  // 3. MD5-хеш випадкового рядка\n  const encoder = new TextEncoder();\n  const data = encoder.encode(randomStr);\n  const md5Buffer = await crypto.subtle.digest(\"MD5\", data);\n\n  const md5hex = [...new Uint8Array(md5Buffer)]\n    .map(b => b.toString(16).padStart(2, '0')).join('');\n\n  // 4. Ще один випадковий рядок\n  const randomSuffix = crypto.getRandomValues(new Uint8Array(6))\n    .map(b => b.toString(36)).join('');\n\n  // 5. Формування \"UUID\"\n  const customUUID = `${timestamp}-${md5hex}-${randomSuffix}`;\n\n  return customUUID;\n}\n\ngenerateCustomUUID().then(console.log);",
    "date": "2025-06-03T18:00:46.421Z",
    "idMsg": "c83df21c-0905-4535-a95a-fd6259257a73"
  },
  {
    "user": "abcd",
    "text": "Та що ж таке",
    "date": "2025-06-03T18:11:56.303Z",
    "idMsg": "e83c2dde-93f3-4f39-9193-afa262bc4ec5"
  },
  {
    "user": "abcd",
    "text": "😡",
    "date": "2025-06-03T18:13:34.192Z",
    "idMsg": "75d676db-3002-40f3-8a38-e6b9f551e71b"
  },
  {
    "user": "abcd",
    "text": "А",
    "date": "2025-06-03T18:14:02.983Z",
    "idMsg": "9b92cd5b-0c74-4168-be09-dc19004406f5"
  },
  {
    "user": "abcd",
    "text": "Хи",
    "date": "2025-06-03T18:14:09.046Z",
    "idMsg": "1d1b563c-664f-4725-84e0-7d350f501d73"
  },
  {
    "user": "abcd",
    "text": "Хм*",
    "date": "2025-06-03T18:14:14.688Z",
    "idMsg": "d8dbd028-00bc-49c8-96c9-9ee0a6a1f70e"
  },
  {
    "user": "testuser1212321",
    "text": "AAA\n\naaa",
    "date": "2025-06-03T18:15:28.990Z",
    "idMsg": "db9c0229-a8b8-47d3-a610-ff047a93f0c1"
  },
  {
    "user": "testuser1212321",
    "text": "jjjjjj",
    "date": "2025-06-03T18:15:40.593Z",
    "idMsg": "3c7766bb-b9e7-409d-b0c5-d2b48e0fd8ae"
  },
  {
    "user": "testuser1212321",
    "text": "ооо",
    "date": "2025-06-03T18:15:47.747Z",
    "idMsg": "29928d2d-482e-47f8-97b0-f9febdfd166d"
  },
  {
    "user": "Danilo",
    "text": "тест",
    "date": "2025-06-03T18:19:51.268Z",
    "idMsg": "33ff6842-c536-4093-b4d8-703998078522"
  },
  {
    "user": "Danilo",
    "text": "ясно",
    "date": "2025-06-03T18:20:08.313Z",
    "idMsg": "c9839dd8-176f-4bb5-8b67-61d76f5a51f2"
  },
  {
    "user": "Danilo",
    "text": "примітка: не називати ніки не ascii літерами, бо ламається апі",
    "date": "2025-06-03T18:21:00.387Z",
    "idMsg": "d7447f42-4c7c-4c1f-a73d-4805ea7c9d4b"
  },
  {
    "user": "Danilo",
    "text": "🇰🇷",
    "date": "2025-06-03T18:29:43.116Z",
    "idMsg": "268dc386-c557-4e84-a67f-3d70cb3875bc"
  },
  {
    "user": "Danilo",
    "text": "🇺🇦",
    "date": "2025-06-03T18:29:53.479Z",
    "idMsg": "66e6124d-d106-4f3a-856c-36ab0cd655c7"
  },
  {
    "user": "Danilo",
    "text": "🇪🇺",
    "date": "2025-06-03T18:30:25.097Z",
    "idMsg": "8d2d5d83-9b1f-44ee-adee-082ac7e6eae9"
  },
  {
    "user": "Danilo",
    "text": "малі але працюють. як кажуть \"якщо працює - не чіпай\"",
    "date": "2025-06-03T18:31:41.167Z",
    "idMsg": "acee04c1-cad1-447f-9c3a-3f2d1915d6c5"
  },
  {
    "user": "abcd",
    "text": "Мгм",
    "date": "2025-06-03T18:43:05.528Z",
    "idMsg": "dca247a0-a602-429a-a641-eebfb9c6594b"
  },
  {
    "user": "abcd",
    "text": ">  Danilo: 🇰🇷 (21:29)",
    "date": "2025-06-03T18:43:22.026Z",
    "idMsg": "f13030e6-4e0c-404c-b037-6cfd35d8d290"
  },
  {
    "user": "abcd",
    "text": "Ладно",
    "date": "2025-06-03T18:43:27.919Z",
    "idMsg": "84bcf25b-65ab-4ecc-bf97-f4e0c1a84011"
  },
  {
    "user": "abcd",
    "text": "Тест",
    "date": "2025-06-03T18:45:24.636Z",
    "idMsg": "631e37c1-ae7f-4431-a09b-1d9d76636e10"
  },
  {
    "user": "abcd",
    "text": "Щя",
    "date": "2025-06-03T18:45:33.750Z",
    "idMsg": "349a4ae3-1373-4f07-9140-e30bd16e4525"
  },
  {
    "user": "abcd",
    "text": "Тест",
    "date": "2025-06-03T18:46:00.094Z",
    "idMsg": "3a9eda30-391b-4487-8a24-897aa970fee9"
  },
  {
    "user": "dhjkkfd",
    "text": "lzokssoos",
    "date": "2025-06-03T18:54:16.369Z",
    "idMsg": "2b4ca1e1-3bc3-45fd-830f-6af769a03769"
  },
  {
    "user": "dhjkkfd",
    "text": "оо",
    "date": "2025-06-03T18:54:26.042Z",
    "idMsg": "24177dfb-da0e-4b56-ba76-0dd3e453a2ed"
  },
  {
    "user": "FAKE GUEST",
    "text": "Во",
    "date": "2025-06-03T18:54:37.685Z",
    "idMsg": "81fa593e-e3bf-4f1e-b837-3a3a767b005f"
  },
  {
    "user": "dhjkkfd",
    "text": "наконец-то",
    "date": "2025-06-03T18:54:38.290Z",
    "idMsg": "84678666-dbb9-4ecf-af2d-2cb181707c26"
  },
  {
    "user": "FAKE GUEST",
    "text": "Чомусь працює не як треба але ок",
    "date": "2025-06-03T18:54:51.606Z",
    "idMsg": "b86b7af0-d604-40af-9315-a343d6fa9fe7"
  },
  {
    "user": "dhjkkfd",
    "text": "🤪",
    "date": "2025-06-03T18:55:09.804Z",
    "idMsg": "a1417b29-6307-446b-9428-fcb357a45190"
  },
  {
    "user": "danilo",
    "text": "Воно наче й працює але не так як треба",
    "date": "2025-06-03T18:55:21.165Z",
    "idMsg": "7319fe07-4b2e-4fc8-87ef-3b51b0715ba9"
  },
  {
    "user": "dhjkkfd",
    "text": "поняла",
    "date": "2025-06-03T18:55:52.555Z",
    "idMsg": "cbb3251e-ea7d-4285-8428-c9ff8869e979"
  },
  {
    "user": "danilo",
    "text": "Завтра пофіксю",
    "date": "2025-06-03T18:56:09.268Z",
    "idMsg": "dc4a048b-64e2-4019-89e0-217151c2d20f"
  },
  {
    "user": "dhjkkfd",
    "text": "рассказывай как дела",
    "date": "2025-06-03T18:56:22.939Z",
    "idMsg": "f3f86c81-40be-48b4-a540-7e0414c8e2d2"
  },
  {
    "user": "danilo",
    "text": "Нормально, сьогодні працювали дома(траву кошену збирали)",
    "date": "2025-06-03T18:56:52.307Z",
    "idMsg": "e5d7445b-e149-44ef-a292-25680c2aaf22"
  },
  {
    "user": "dhjkkfd",
    "text": "поняла",
    "date": "2025-06-03T18:57:03.020Z",
    "idMsg": "ad21b1c4-c33a-462e-b9ef-bf1d54f56323"
  },
  {
    "user": "danilo",
    "text": "До речі подвійним нажаттям можна відкрити меню(копіювати повідомлення, відповісти та видалити(тільки для власника))",
    "date": "2025-06-03T18:57:34.758Z",
    "idMsg": "f0912f68-9730-45fa-a979-0ada28b2a863"
  },
  {
    "user": "danilo",
    "text": ">  dhjkkfd: поняла (21:57)\nОсь так якось відповідь",
    "date": "2025-06-03T18:57:47.553Z",
    "idMsg": "93161865-e6c2-4b7c-bb77-c85df282c6d4"
  },
  {
    "user": "dhjkkfd",
    "text": ">  danilo: >  dhjkkfd: поняла (21:57)Ось так якось відповідь (21:57)йомайо",
    "date": "2025-06-03T18:58:03.519Z",
    "idMsg": "c2e560f9-3e96-4eaa-ba6c-61f2655861b1"
  },
  {
    "user": "danilo",
    "text": "Во",
    "date": "2025-06-03T18:58:20.598Z",
    "idMsg": "feaf5331-fe3c-4b50-a7b4-893657070345"
  },
  {
    "user": "dhjkkfd",
    "text": "я фигею",
    "date": "2025-06-03T18:58:44.514Z",
    "idMsg": "cb3f8e55-3f1e-4b04-b8eb-d98afed23275"
  },
  {
    "user": "danilo",
    "text": "Там в налаштуваннях є і теми(світла, темна, неонова та типу фентезі але це світла тільки з градієнтом у меню)",
    "date": "2025-06-03T18:59:19.414Z",
    "idMsg": "796427d1-d5b8-45d1-bc02-3284c97e5bf7"
  },
  {
    "user": "dhjkkfd",
    "text": "а якщо ти кинеш комусь ще ссилку на чат,він буде бачити нашу ось цю переписку?я так розумію так",
    "date": "2025-06-03T18:59:36.984Z",
    "idMsg": "ede347c2-cb82-42c8-a6b3-f07e7d9c4fd0"
  },
  {
    "user": "danilo",
    "text": "Ну ще є підсвітка посилань https://example.com",
    "date": "2025-06-03T18:59:46.235Z",
    "idMsg": "3a946358-8d2a-4250-893a-abb1246ef837"
  },
  {
    "user": "Danilo",
    "text": ">  dhjkkfd: а якщо ти кинеш комусь ще ссилку на чат,він буде бачити нашу ось цю переписку?я так розумію так (21:59)\nпоки до цього чату мають доступ 5 осіб(ти, я, алла василівна, та 3 моїх інтернет друга)",
    "date": "2025-06-03T19:01:17.347Z",
    "idMsg": "a6cadcd7-0aec-4c0d-8fbd-3dc664bf7f36"
  },
  {
    "user": "Danilo",
    "text": "але я можу маніпулювати базою даних повідомлень",
    "date": "2025-06-03T19:01:40.006Z",
    "idMsg": "bd13a597-c37f-4ff2-8dc6-a8c6a2072672"
  },
  {
    "user": "Sofa",
    "text": "наприклад це зараз зміниться на іншк",
    "date": "2025-06-03T19:02:00.182Z",
    "idMsg": "7b0132fa-7eba-46a8-b4c4-8e96df59c7ac"
  },
  {
    "user": "Danilo",
    "text": "тепер це Sofa а не Danilo",
    "date": "2025-06-03T19:02:53.137Z",
    "idMsg": "7ae53e61-24cd-452e-bf03-a9b3a7b80839"
  },
  {
    "user": "dhjkkfd",
    "text": "как все сложно",
    "date": "2025-06-03T19:03:58.058Z",
    "idMsg": "59088f32-c039-4906-96c1-2128262f4fac"
  },
  {
    "user": "danilo",
    "text": "🇯🇵",
    "date": "2025-06-04T05:08:27.924Z",
    "idMsg": "e9487a2a-1694-4fc5-bc63-4e8e66adb219"
  },
  {
    "user": "Danilo",
    "text": "икси",
    "date": "2025-06-04T18:06:13.054Z",
    "idMsg": "85b1cefa-ebea-4d6b-b2d4-0d533b47540e"
  }
]